tosca/__init__.py
tosca/_tosca.py
tosca/builtin_types.py
tosca/loader.py
tosca/py.typed
tosca/python2yaml.py
tosca/scalars.py
tosca/yaml2python.py
tosca/vendor/toscaparser/__init__.py
tosca/vendor/toscaparser/activities.py
tosca/vendor/toscaparser/artifacts.py
tosca/vendor/toscaparser/capabilities.py
tosca/vendor/toscaparser/dataentity.py
tosca/vendor/toscaparser/entity_template.py
tosca/vendor/toscaparser/functions.py
tosca/vendor/toscaparser/groups.py
tosca/vendor/toscaparser/imports.py
tosca/vendor/toscaparser/nodetemplate.py
tosca/vendor/toscaparser/parameters.py
tosca/vendor/toscaparser/policy.py
tosca/vendor/toscaparser/properties.py
tosca/vendor/toscaparser/relationship_template.py
tosca/vendor/toscaparser/repositories.py
tosca/vendor/toscaparser/reservation.py
tosca/vendor/toscaparser/shell.py
tosca/vendor/toscaparser/steps.py
tosca/vendor/toscaparser/substitution_mappings.py
tosca/vendor/toscaparser/topology_template.py
tosca/vendor/toscaparser/tosca_template.py
tosca/vendor/toscaparser/tpl_relationship_graph.py
tosca/vendor/toscaparser/triggers.py
tosca/vendor/toscaparser/unsupportedtype.py
tosca/vendor/toscaparser/workflow.py
tosca/vendor/toscaparser/common/__init__.py
tosca/vendor/toscaparser/common/exception.py
tosca/vendor/toscaparser/elements/TOSCA_definition_1_0.yaml
tosca/vendor/toscaparser/elements/TOSCA_definition_1_3.yaml
tosca/vendor/toscaparser/elements/__init__.py
tosca/vendor/toscaparser/elements/artifacttype.py
tosca/vendor/toscaparser/elements/attribute_definition.py
tosca/vendor/toscaparser/elements/capabilitytype.py
tosca/vendor/toscaparser/elements/constraints.py
tosca/vendor/toscaparser/elements/datatype.py
tosca/vendor/toscaparser/elements/entity_type.py
tosca/vendor/toscaparser/elements/grouptype.py
tosca/vendor/toscaparser/elements/interfaces.py
tosca/vendor/toscaparser/elements/nodetype.py
tosca/vendor/toscaparser/elements/policytype.py
tosca/vendor/toscaparser/elements/portspectype.py
tosca-0.1.0.dist-info/LICENSE
tosca-0.1.0.dist-info/METADATA
tosca-0.1.0.dist-info/WHEEL
tosca-0.1.0.dist-info/top_level.txt
tosca-0.1.0.dist-info/RECORD
