Metadata-Version: 2.1
Name: tosca
Version: 0.1.0
Summary: A library for representing TOSCA (Topology and Orchestration Specification for Cloud Applications) in Python
Author-email: Adam Souzis <adam@onecommons.org>
Project-URL: Homepage, https://www.unfurl.cloud
Project-URL: Documentation, https://docs.unfurl.run/dsl.html
Project-URL: Repository, https://github.com/onecommons/unfurl/tree/main/tosca-package
Project-URL: Changelog, https://github.com/onecommons/unfurl/blob/main/CHANGELOG.md
Classifier: Programming Language :: Python :: 3
Classifier: License :: OSI Approved :: MIT License
Classifier: Operating System :: OS Independent
Classifier: Programming Language :: Python :: 3.8
Classifier: Programming Language :: Python :: 3.9
Classifier: Programming Language :: Python :: 3.10
Classifier: Programming Language :: Python :: 3.11
Classifier: Programming Language :: Python :: 3.12
Classifier: Programming Language :: Python :: 3.13
Requires-Python: >=3.8
License-File: LICENSE
Requires-Dist: black>=24.3.0
Requires-Dist: typing_extensions>=4.7.1
Requires-Dist: RestrictedPython>=7.4
